{
  "_version": 3,
  "_app": "CHM Church of God",
  "_section": "Teams",
  "_collection": "teams",
  "_exportedAt": "2026-07-17T05:54:49.126Z",
  "_note": "Upload as chm-teams.json to GitHub repo root — auto-loaded by Teams page",
  "teams": [
    {
      "icon": "📣",
      "name": "Communications Team",
      "desc": "Crafting and distributing church announcements, newsletters, and internal communications.",
      "category": "Operations",
      "order": 33,
      "leader": "",
      "photo": "",
      "id": "mroiwjfzt851t",
      "collection": "teams",
      "_status": "draft",
      "status": "draft",
      "archived": false,
      "mediaUrl": "",
      "imageUrl": "",
      "photoUrl": "",
      "thumbnailUrl": "",
      "_updatedAt": 1784267672687,
      "updatedAt": 1784267672687,
      "_publishedAt": "",
      "publishedAt": ""
    },
    {
      "icon": "📊",
      "name": "Strategic Planning Team",
      "desc": "Supporting leadership with research, data, and planning to guide CHM's growth and vision.",
      "category": "Operations",
      "order": 32,
      "leader": "",
      "photo": "",
      "id": "mroiwjfrwbf5q",
      "collection": "teams",
      "_status": "draft",
      "status": "draft",
      "archived": false,
      "mediaUrl": "",
      "imageUrl": "",
      "photoUrl": "",
      "thumbnailUrl": "",
      "_updatedAt": 1784267672679,
      "updatedAt": 1784267672679,
      "_publishedAt": "",
      "publishedAt": ""
    },
    {
      "icon": "🔧",
      "name": "Facilities Team",
      "desc": "Maintaining and improving church facilities to ensure safe, functional, and welcoming environments.",
      "category": "Operations",
      "order": 31,
      "leader": "",
      "photo": "",
      "id": "mroiwjfn7ckgj",
      "collection": "teams",
      "_status": "draft",
      "status": "draft",
      "archived": false,
      "mediaUrl": "",
      "imageUrl": "",
      "photoUrl": "",
      "thumbnailUrl": "",
      "_updatedAt": 1784267672675,
      "updatedAt": 1784267672675,
      "_publishedAt": "",
      "publishedAt": ""
    },
    {
      "icon": "📦",
      "name": "Events Logistics Team",
      "desc": "Coordinating setup, teardown, and logistics for all church services, conferences, and special events.",
      "category": "Operations",
      "order": 30,
      "leader": "",
      "photo": "",
      "id": "mroiwjfk6ihqw",
      "collection": "teams",
      "_status": "draft",
      "status": "draft",
      "archived": false,
      "mediaUrl": "",
      "imageUrl": "",
      "photoUrl": "",
      "thumbnailUrl": "",
      "_updatedAt": 1784267672672,
      "updatedAt": 1784267672672,
      "_publishedAt": "",
      "publishedAt": ""
    },
    {
      "icon": "💰",
      "name": "Finance & Stewardship Team",
      "desc": "Overseeing the church budget, accounting, and financial stewardship with transparency and excellence.",
      "category": "Operations",
      "order": 29,
      "leader": "",
      "photo": "",
      "id": "mroiwjfhme79p",
      "collection": "teams",
      "_status": "draft",
      "status": "draft",
      "archived": false,
      "mediaUrl": "",
      "imageUrl": "",
      "photoUrl": "",
      "thumbnailUrl": "",
      "_updatedAt": 1784267672669,
      "updatedAt": 1784267672669,
      "_publishedAt": "",
      "publishedAt": ""
    },
    {
      "icon": "📋",
      "name": "Administration Team",
      "desc": "Managing church records, correspondence, and administrative processes with precision and integrity.",
      "category": "Operations",
      "order": 28,
      "leader": "",
      "photo": "",
      "id": "mroiwjfa5mu1c",
      "collection": "teams",
      "_status": "draft",
      "status": "draft",
      "archived": false,
      "mediaUrl": "",
      "imageUrl": "",
      "photoUrl": "",
      "thumbnailUrl": "",
      "_updatedAt": 1784267672662,
      "updatedAt": 1784267672662,
      "_publishedAt": "",
      "publishedAt": ""
    },
    {
      "icon": "🤗",
      "name": "Grief Support Team",
      "desc": "Walking alongside those experiencing loss with compassionate care, resources, and community.",
      "category": "Care & Support",
      "order": 27,
      "leader": "",
      "photo": "",
      "id": "mroiwjf6bw78z",
      "collection": "teams",
      "_status": "draft",
      "status": "draft",
      "archived": false,
      "mediaUrl": "",
      "imageUrl": "",
      "photoUrl": "",
      "thumbnailUrl": "",
      "_updatedAt": 1784267672658,
      "updatedAt": 1784267672658,
      "_publishedAt": "",
      "publishedAt": ""
    },
    {
      "icon": "🧒",
      "name": "Nursery Team",
      "desc": "Providing safe, loving care for infants and toddlers during services so parents can worship freely.",
      "category": "Care & Support",
      "order": 26,
      "leader": "",
      "photo": "",
      "id": "mroiwjf3evmhd",
      "collection": "teams",
      "_status": "draft",
      "status": "draft",
      "archived": false,
      "mediaUrl": "",
      "imageUrl": "",
      "photoUrl": "",
      "thumbnailUrl": "",
      "_updatedAt": 1784267672655,
      "updatedAt": 1784267672655,
      "_publishedAt": "",
      "publishedAt": ""
    },
    {
      "icon": "👵",
      "name": "Senior Care Team",
      "desc": "Visiting, checking in on, and ministering to our elderly members who may be homebound or in care facilities.",
      "category": "Care & Support",
      "order": 25,
      "leader": "",
      "photo": "",
      "id": "mroiwjf0h02t7",
      "collection": "teams",
      "_status": "draft",
      "status": "draft",
      "archived": false,
      "mediaUrl": "",
      "imageUrl": "",
      "photoUrl": "",
      "thumbnailUrl": "",
      "_updatedAt": 1784267672652,
      "updatedAt": 1784267672652,
      "_publishedAt": "",
      "publishedAt": ""
    },
    {
      "icon": "🍱",
      "name": "Benevolence Team",
      "desc": "Providing practical assistance with food, utilities, and emergency needs for families in crisis.",
      "category": "Care & Support",
      "order": 24,
      "leader": "",
      "photo": "",
      "id": "mroiwjerubcc2",
      "collection": "teams",
      "_status": "draft",
      "status": "draft",
      "archived": false,
      "mediaUrl": "",
      "imageUrl": "",
      "photoUrl": "",
      "thumbnailUrl": "",
      "_updatedAt": 1784267672643,
      "updatedAt": 1784267672643,
      "_publishedAt": "",
      "publishedAt": ""
    },
    {
      "icon": "🧠",
      "name": "Counseling Team",
      "desc": "Certified biblical counselors offering confidential guidance for personal and family challenges.",
      "category": "Care & Support",
      "order": 23,
      "leader": "",
      "photo": "",
      "id": "mroiwjepamg8n",
      "collection": "teams",
      "_status": "draft",
      "status": "draft",
      "archived": false,
      "mediaUrl": "",
      "imageUrl": "",
      "photoUrl": "",
      "thumbnailUrl": "",
      "_updatedAt": 1784267672641,
      "updatedAt": 1784267672641,
      "_publishedAt": "",
      "publishedAt": ""
    },
    {
      "icon": "💙",
      "name": "Pastoral Care Team",
      "desc": "Providing compassionate support through hospital visits, home visits, and crisis counseling.",
      "category": "Care & Support",
      "order": 22,
      "leader": "",
      "photo": "",
      "id": "mroiwjelggoq5",
      "collection": "teams",
      "_status": "draft",
      "status": "draft",
      "archived": false,
      "mediaUrl": "",
      "imageUrl": "",
      "photoUrl": "",
      "thumbnailUrl": "",
      "_updatedAt": 1784267672637,
      "updatedAt": 1784267672637,
      "_publishedAt": "",
      "publishedAt": ""
    },
    {
      "icon": "📱",
      "name": "Social Media Team",
      "desc": "Creating and publishing content that engages and grows CHM's online community and witness.",
      "category": "Media & Technology",
      "order": 21,
      "leader": "",
      "photo": "",
      "id": "mroiwjec5zk7a",
      "collection": "teams",
      "_status": "draft",
      "status": "draft",
      "archived": false,
      "mediaUrl": "",
      "imageUrl": "",
      "photoUrl": "",
      "thumbnailUrl": "",
      "_updatedAt": 1784267672628,
      "updatedAt": 1784267672628,
      "_publishedAt": "",
      "publishedAt": ""
    },
    {
      "icon": "💻",
      "name": "IT & Website Team",
      "desc": "Managing technology infrastructure, the church website, and digital communications.",
      "category": "Media & Technology",
      "order": 20,
      "leader": "",
      "photo": "",
      "id": "mroiwjeai4zka",
      "collection": "teams",
      "_status": "draft",
      "status": "draft",
      "archived": false,
      "mediaUrl": "",
      "imageUrl": "",
      "photoUrl": "",
      "thumbnailUrl": "",
      "_updatedAt": 1784267672626,
      "updatedAt": 1784267672626,
      "_publishedAt": "",
      "publishedAt": ""
    },
    {
      "icon": "📸",
      "name": "Photography Team",
      "desc": "Capturing meaningful moments from services, events, and ministry for the church archive and media use.",
      "category": "Media & Technology",
      "order": 19,
      "leader": "",
      "photo": "",
      "id": "mroiwje9guizr",
      "collection": "teams",
      "_status": "draft",
      "status": "draft",
      "archived": false,
      "mediaUrl": "",
      "imageUrl": "",
      "photoUrl": "",
      "thumbnailUrl": "",
      "_updatedAt": 1784267672625,
      "updatedAt": 1784267672625,
      "_publishedAt": "",
      "publishedAt": ""
    },
    {
      "icon": "🔊",
      "name": "Sound Engineering Team",
      "desc": "Managing audio systems and ensuring crystal-clear sound for every service and event.",
      "category": "Media & Technology",
      "order": 18,
      "leader": "",
      "photo": "",
      "id": "mroiwje7lortc",
      "collection": "teams",
      "_status": "draft",
      "status": "draft",
      "archived": false,
      "mediaUrl": "",
      "imageUrl": "",
      "photoUrl": "",
      "thumbnailUrl": "",
      "_updatedAt": 1784267672623,
      "updatedAt": 1784267672623,
      "_publishedAt": "",
      "publishedAt": ""
    },
    {
      "icon": "🎬",
      "name": "Video Production Team",
      "desc": "Filming, editing, and producing high-quality video content for sermons, announcements, and ministry.",
      "category": "Media & Technology",
      "order": 17,
      "leader": "",
      "photo": "",
      "id": "mroiwje64avfz",
      "collection": "teams",
      "_status": "draft",
      "status": "draft",
      "archived": false,
      "mediaUrl": "",
      "imageUrl": "",
      "photoUrl": "",
      "thumbnailUrl": "",
      "_updatedAt": 1784267672622,
      "updatedAt": 1784267672622,
      "_publishedAt": "",
      "publishedAt": ""
    },
    {
      "icon": "📺",
      "name": "Livestream Team",
      "desc": "Producing and broadcasting live services across YouTube, Facebook, and other streaming platforms.",
      "category": "Media & Technology",
      "order": 16,
      "leader": "",
      "photo": "",
      "id": "mroiwje5hh81c",
      "collection": "teams",
      "_status": "draft",
      "status": "draft",
      "archived": false,
      "mediaUrl": "",
      "imageUrl": "",
      "photoUrl": "",
      "thumbnailUrl": "",
      "_updatedAt": 1784267672621,
      "updatedAt": 1784267672621,
      "_publishedAt": "",
      "publishedAt": ""
    },
    {
      "icon": "🌿",
      "name": "Grounds & Landscaping Team",
      "desc": "Maintaining the external appearance of our church property with excellence and care.",
      "category": "Hospitality",
      "order": 15,
      "leader": "",
      "photo": "",
      "id": "mroiwje3fcf2o",
      "collection": "teams",
      "_status": "draft",
      "status": "draft",
      "archived": false,
      "mediaUrl": "",
      "imageUrl": "",
      "photoUrl": "",
      "thumbnailUrl": "",
      "_updatedAt": 1784267672619,
      "updatedAt": 1784267672619,
      "_publishedAt": "",
      "publishedAt": ""
    },
    {
      "icon": "🧹",
      "name": "Cleaning & Maintenance Team",
      "desc": "Keeping our facilities clean, organized, and ready for every service and event.",
      "category": "Hospitality",
      "order": 14,
      "leader": "",
      "photo": "",
      "id": "mroiwjdy43ibl",
      "collection": "teams",
      "_status": "draft",
      "status": "draft",
      "archived": false,
      "mediaUrl": "",
      "imageUrl": "",
      "photoUrl": "",
      "thumbnailUrl": "",
      "_updatedAt": 1784267672614,
      "updatedAt": 1784267672614,
      "_publishedAt": "",
      "publishedAt": ""
    },
    {
      "icon": "🎁",
      "name": "New Members Team",
      "desc": "Walking alongside new converts and new members, helping them connect and grow in CHM.",
      "category": "Hospitality",
      "order": 13,
      "leader": "",
      "photo": "",
      "id": "mroiwjdwkhc5y",
      "collection": "teams",
      "_status": "draft",
      "status": "draft",
      "archived": false,
      "mediaUrl": "",
      "imageUrl": "",
      "photoUrl": "",
      "thumbnailUrl": "",
      "_updatedAt": 1784267672612,
      "updatedAt": 1784267672612,
      "_publishedAt": "",
      "publishedAt": ""
    },
    {
      "icon": "🍽️",
      "name": "Kitchen & Catering Team",
      "desc": "Preparing and serving meals for church events, banquets, and special ministry gatherings.",
      "category": "Hospitality",
      "order": 12,
      "leader": "",
      "photo": "",
      "id": "mroiwjdt7mmqo",
      "collection": "teams",
      "_status": "draft",
      "status": "draft",
      "archived": false,
      "mediaUrl": "",
      "imageUrl": "",
      "photoUrl": "",
      "thumbnailUrl": "",
      "_updatedAt": 1784267672609,
      "updatedAt": 1784267672609,
      "_publishedAt": "",
      "publishedAt": ""
    },
    {
      "icon": "🌸",
      "name": "Sanctuary Decoration Team",
      "desc": "Creating a beautiful, inspiring worship environment through floral arrangements and themed décor.",
      "category": "Hospitality",
      "order": 11,
      "leader": "",
      "photo": "",
      "id": "mroiwjdshmwpu",
      "collection": "teams",
      "_status": "draft",
      "status": "draft",
      "archived": false,
      "mediaUrl": "",
      "imageUrl": "",
      "photoUrl": "",
      "thumbnailUrl": "",
      "_updatedAt": 1784267672608,
      "updatedAt": 1784267672608,
      "_publishedAt": "",
      "publishedAt": ""
    },
    {
      "icon": "🤝",
      "name": "Welcome & Ushering Team",
      "desc": "Greeting guests and members with warmth, directing seating, and setting a culture of belonging.",
      "category": "Hospitality",
      "order": 10,
      "leader": "",
      "photo": "",
      "id": "mroiwjdq9rscn",
      "collection": "teams",
      "_status": "draft",
      "status": "draft",
      "archived": false,
      "mediaUrl": "",
      "imageUrl": "",
      "photoUrl": "",
      "thumbnailUrl": "",
      "_updatedAt": 1784267672606,
      "updatedAt": 1784267672606,
      "_publishedAt": "",
      "publishedAt": ""
    },
    {
      "icon": "🚑",
      "name": "First Aid & Medical Team",
      "desc": "Certified first responders ready to provide immediate medical assistance when needed.",
      "category": "Security & Safety",
      "order": 9,
      "leader": "",
      "photo": "",
      "id": "mroiwjdpr314m",
      "collection": "teams",
      "_status": "draft",
      "status": "draft",
      "archived": false,
      "mediaUrl": "",
      "imageUrl": "",
      "photoUrl": "",
      "thumbnailUrl": "",
      "_updatedAt": 1784267672605,
      "updatedAt": 1784267672605,
      "_publishedAt": "",
      "publishedAt": ""
    },
    {
      "icon": "🅿️",
      "name": "Parking & Traffic Team",
      "desc": "Directing traffic and assisting with parking to create a smooth and welcoming arrival experience.",
      "category": "Security & Safety",
      "order": 8,
      "leader": "",
      "photo": "",
      "id": "mroiwjdojsjrm",
      "collection": "teams",
      "_status": "draft",
      "status": "draft",
      "archived": false,
      "mediaUrl": "",
      "imageUrl": "",
      "photoUrl": "",
      "thumbnailUrl": "",
      "_updatedAt": 1784267672604,
      "updatedAt": 1784267672604,
      "_publishedAt": "",
      "publishedAt": ""
    },
    {
      "icon": "🛡️",
      "name": "Church Security Team",
      "desc": "Professionally trained team ensuring the safety and security of all congregation members during services.",
      "category": "Security & Safety",
      "order": 7,
      "leader": "",
      "photo": "",
      "id": "mroiwjdm1g37k",
      "collection": "teams",
      "_status": "draft",
      "status": "draft",
      "archived": false,
      "mediaUrl": "",
      "imageUrl": "",
      "photoUrl": "",
      "thumbnailUrl": "",
      "_updatedAt": 1784267672602,
      "updatedAt": 1784267672602,
      "_publishedAt": "",
      "publishedAt": ""
    },
    {
      "icon": "📿",
      "name": "Prayer Chain Team",
      "desc": "A network of prayer partners available around the clock to receive and respond to urgent prayer requests.",
      "category": "Prayer & Worship",
      "order": 6,
      "leader": "",
      "photo": "",
      "id": "mroiwjdd02xnd",
      "collection": "teams",
      "_status": "draft",
      "status": "draft",
      "archived": false,
      "mediaUrl": "",
      "imageUrl": "",
      "photoUrl": "",
      "thumbnailUrl": "",
      "_updatedAt": 1784267672593,
      "updatedAt": 1784267672593,
      "_publishedAt": "",
      "publishedAt": ""
    },
    {
      "icon": "🔔",
      "name": "Altar Call Team",
      "desc": "Trained ministers meeting individuals at the altar for prayer, counsel, and spiritual support.",
      "category": "Prayer & Worship",
      "order": 5,
      "leader": "",
      "photo": "",
      "id": "mroiwjdch68v0",
      "collection": "teams",
      "_status": "draft",
      "status": "draft",
      "archived": false,
      "mediaUrl": "",
      "imageUrl": "",
      "photoUrl": "",
      "thumbnailUrl": "",
      "_updatedAt": 1784267672592,
      "updatedAt": 1784267672592,
      "_publishedAt": "",
      "publishedAt": ""
    },
    {
      "icon": "🎹",
      "name": "Praise & Dance Team",
      "desc": "Expressing worship through creative dance, flags, and movement as unto the Lord.",
      "category": "Prayer & Worship",
      "order": 4,
      "leader": "",
      "photo": "",
      "id": "mroiwjdaiah0w",
      "collection": "teams",
      "_status": "draft",
      "status": "draft",
      "archived": false,
      "mediaUrl": "",
      "imageUrl": "",
      "photoUrl": "",
      "thumbnailUrl": "",
      "_updatedAt": 1784267672590,
      "updatedAt": 1784267672590,
      "_publishedAt": "",
      "publishedAt": ""
    },
    {
      "icon": "🎵",
      "name": "Worship Team",
      "desc": "Musicians, singers, and worshippers leading the congregation into Spirit-filled worship each service.",
      "category": "Prayer & Worship",
      "order": 3,
      "leader": "",
      "photo": "",
      "id": "mroiwjd9rp24h",
      "collection": "teams",
      "_status": "draft",
      "status": "draft",
      "archived": false,
      "mediaUrl": "",
      "imageUrl": "",
      "photoUrl": "",
      "thumbnailUrl": "",
      "_updatedAt": 1784267672589,
      "updatedAt": 1784267672589,
      "_publishedAt": "",
      "publishedAt": ""
    },
    {
      "icon": "⚔️",
      "name": "Intercessory Prayer Team",
      "desc": "Standing in the gap through focused, targeted intercession for specific needs, leaders, and nations.",
      "category": "Prayer & Worship",
      "order": 2,
      "leader": "",
      "photo": "",
      "id": "mroiwjd84k6fb",
      "collection": "teams",
      "_status": "draft",
      "status": "draft",
      "archived": false,
      "mediaUrl": "",
      "imageUrl": "",
      "photoUrl": "",
      "thumbnailUrl": "",
      "_updatedAt": 1784267672588,
      "updatedAt": 1784267672588,
      "_publishedAt": "",
      "publishedAt": ""
    },
    {
      "icon": "🙏",
      "name": "Early Morning Prayer Team",
      "desc": "Interceding before dawn for the church and community, setting the spiritual atmosphere for each day.",
      "category": "Prayer & Worship",
      "order": 1,
      "leader": "",
      "photo": "",
      "id": "mroiwjd6aiddo",
      "collection": "teams",
      "_status": "draft",
      "status": "draft",
      "archived": false,
      "mediaUrl": "",
      "imageUrl": "",
      "photoUrl": "",
      "thumbnailUrl": "",
      "_updatedAt": 1784267672586,
      "updatedAt": 1784267672586,
      "_publishedAt": "",
      "publishedAt": ""
    },
    {
      "icon": "🙏",
      "name": "Intercessory Prayer Team",
      "category": "Prayer & Worship",
      "order": 99,
      "desc": "jjhbjbbjbj",
      "leader": "",
      "photo": "https://m.media-amazon.com/images/I/61sNfxDTwyL._AC_UF1000,1000_QL80_.jpg",
      "id": "mqybp4thm73hb",
      "collection": "teams",
      "_status": "published",
      "status": "published",
      "archived": false,
      "mediaUrl": "",
      "imageUrl": "",
      "photoUrl": "",
      "thumbnailUrl": "",
      "_updatedAt": 1782683449253,
      "updatedAt": 1782683449253,
      "_publishedAt": 1782683449253,
      "publishedAt": 1782683449253
    }
  ],
  "hero": []
}